MANIFEST.in
README.rst
setup.py
fh_django_gcs.egg-info/PKG-INFO
fh_django_gcs.egg-info/SOURCES.txt
fh_django_gcs.egg-info/dependency_links.txt
fh_django_gcs.egg-info/top_level.txt
gcs/__init__.py
gcs/settings.py
gcs/storage.py
gcs/utils.py