Metadata-Version: 1.0
Name: fh-django-gcs
Version: 0.2.0
Summary: A Django app to provide a GCS storage engine for App Engine
Home-page: https://gitlab.com/futurehaus/django-gcs
Author: UNKNOWN
Author-email: jturmel@gmail.com
License: UNKNOWN
Platform: UNKNOWN
